{
	"name": "emp_few_cols_SELECT",
	"properties": {
		"type": "MappingDataFlow",
		"typeProperties": {
			"sources": [
				{
					"dataset": {
						"referenceName": "Dynamic_Dataset_DB",
						"type": "DatasetReference"
					},
					"name": "source1"
				}
			],
			"sinks": [
				{
					"dataset": {
						"referenceName": "Dynamic_Dataset_DB",
						"type": "DatasetReference"
					},
					"name": "sink1"
				}
			],
			"transformations": [
				{
					"name": "select1"
				}
			],
			"scriptLines": [
				"source(output(",
				"          EMPNO as decimal(4,0),",
				"          ENAME as string,",
				"          JOB as string,",
				"          MGR as decimal(4,0),",
				"          HIREDATE as timestamp,",
				"          SAL as decimal(7,2),",
				"          COMM as decimal(7,2),",
				"          DEPTNO as decimal(2,0)",
				"     ),",
				"     allowSchemaDrift: true,",
				"     validateSchema: false,",
				"     isolationLevel: 'READ_UNCOMMITTED',",
				"     query: 'select * from emp',",
				"     format: 'query') ~> source1",
				"source1 select(mapColumn(",
				"          EMPNO,",
				"          ENAME,",
				"          JOB,",
				"          SAL,",
				"          DEPTNO",
				"     ),",
				"     skipDuplicateMapInputs: true,",
				"     skipDuplicateMapOutputs: true) ~> select1",
				"select1 sink(allowSchemaDrift: true,",
				"     validateSchema: false,",
				"     deletable:false,",
				"     insertable:true,",
				"     updateable:false,",
				"     upsertable:false,",
				"     format: 'table',",
				"     skipDuplicateMapInputs: true,",
				"     skipDuplicateMapOutputs: true,",
				"     errorHandlingOption: 'stopOnFirstError',",
				"     mapColumn(",
				"          EMPNO,",
				"          ENAME,",
				"          JOB,",
				"          SAL,",
				"          DEPTNO",
				"     )) ~> sink1"
			]
		}
	}
}